{
  "repository": "Podcast Player",
  "bugs": [
    {
      "comment": "Bug #1 - flexbox",
      "report_text": "The control buttons are stacking vertically in a column instead of displaying horizontally in a row.",
      "bug_category": "Layout",
      "bug_type": "flexbox",
      "file_modified": "src/components/Controls.jsx",
      "line_number": 5,
      "neg_code": "<div className=\"flex items-center justify-center gap-6 mb-8\">",
      "pos_code": "<div className=\"flex flex-col items-center justify-center gap-6 mb-8\">",
      "css_selector": "div:has(button[title=\"Volume\"])",
      "bounding_box": {
        "x": 113,
        "y": 678,
        "width": 670,
        "height": 240
      }
    },
    {
      "comment": "Bug #2 - width",
      "report_text": "The play button is excessively large, consuming most of the viewport and breaking the layout.",
      "bug_category": "Layout",
      "bug_type": "width",
      "file_modified": "src/components/Controls.jsx",
      "line_number": 21,
      "neg_code": "className=\"w-20 h-20 bg-gradient-to-br from-purple-500 to-pink-500 rounded-full flex items-center justify-center shadow-2xl hover:shadow-purple-500/50 hover:scale-110 transition transform text-white\"",
      "pos_code": "className=\"w-200 h-200 bg-gradient-to-br from-purple-500 to-pink-500 rounded-full flex items-center justify-center shadow-2xl hover:shadow-purple-500/50 hover:scale-110 transition transform text-white\"",
      "css_selector": "button.rounded-full.bg-gradient-to-br",
      "bounding_box": {
        "x": 240,
        "y": 500,
        "width": 800,
        "height": 600
      }
    },
    {
      "comment": "Bug #3 - z-index",
      "report_text": "The header is hidden behind other page content when scrolling, making it inaccessible.",
      "bug_category": "Layers",
      "bug_type": "z-index",
      "file_modified": "src/components/Header.jsx",
      "line_number": 5,
      "neg_code": "<header className=\"border-b border-gray-800 bg-gray-900/50 backdrop-blur-md sticky top-0 z-20\">",
      "pos_code": "<header className=\"border-b border-gray-800 bg-gray-900/50 backdrop-blur-md sticky top-0 z-0\">",
      "css_selector": "header",
      "bounding_box": {
        "x": 0,
        "y": 0,
        "width": 1280,
        "height": 85
      }
    },
    {
      "comment": "Bug #4 - text-color",
      "report_text": "The app logo text is rendered in plain white instead of displaying the intended gradient color effect.",
      "bug_category": "Color",
      "bug_type": "text-color",
      "file_modified": "src/components/Header.jsx",
      "line_number": 10,
      "neg_code": "<h1 className=\"text-2xl font-bold bg-gradient-to-r from-purple-400 to-pink-400 bg-clip-text text-transparent\">PodHub</h1>",
      "pos_code": "<h1 className=\"text-2xl font-bold bg-gradient-to-r from-purple-400 to-pink-400 bg-clip-text text-white\">PodHub</h1>",
      "css_selector": "header h1",
      "bounding_box": {
        "x": 133,
        "y": 26,
        "width": 91,
        "height": 32
      }
    },
    {
      "comment": "Bug #5 - margin",
      "report_text": "The album artwork is offset from its intended position and overlaps the surrounding UI elements.",
      "bug_category": "Spacing",
      "bug_type": "margin",
      "file_modified": "src/components/Player.jsx",
      "line_number": 30,
      "neg_code": "<div className=\"flex justify-center mb-8 relative\">",
      "pos_code": "<div className=\"flex justify-center mb-8 relative -m-16\">",
      "css_selector": "div:has(div.w-80.h-80.rounded-2xl.shadow-2xl)",
      "bounding_box": {
        "x": 49,
        "y": 80,
        "width": 798,
        "height": 500
      }
    },
    {
      "comment": "Bug #6 - position",
      "report_text": "The LIVE indicator badge stretches to cover the entire album artwork instead of appearing as a small badge.",
      "bug_category": "Layers",
      "bug_type": "position",
      "file_modified": "src/components/Player.jsx",
      "line_number": 40,
      "neg_code": "<div className=\"absolute -top-4 right-0 px-4 py-2 bg-red-500 rounded-full text-sm font-bold flex items-center gap-2 shadow-lg\">",
      "pos_code": "<div className=\"absolute inset-0 px-4 py-2 bg-red-500 rounded-full text-sm font-bold flex items-center gap-2 shadow-lg\">",
      "css_selector": "div:has-text('LIVE')",
      "bounding_box": {
        "x": 480,
        "y": 80,
        "width": 320,
        "height": 320
      }
    },
    {
      "comment": "Bug #7 - padding",
      "report_text": "The episode list button has excessive internal spacing, creating an unnaturally oversized and awkward appearance.",
      "bug_category": "Spacing",
      "bug_type": "padding",
      "file_modified": "src/components/EpisodeList.jsx",
      "line_number": 16,
      "neg_code": "className=\"w-full font-bold mb-4 flex items-center justify-between hover:text-purple-400 transition\"",
      "pos_code": "className=\"w-full font-bold mb-4 flex items-center justify-between hover:text-purple-400 transition px-40 py-20\"",
      "css_selector": "button:has-text('Episodes')",
      "bounding_box": {
        "x": 873,
        "y": 823,
        "width": 500,
        "height": 208
      }
    },
    {
      "comment": "Bug #8 - border-radius",
      "report_text": "The podcast list buttons are excessively rounded, appearing as pill shapes rather than having subtle corner rounding.",
      "bug_category": "Layout",
      "bug_type": "border-radius",
      "file_modified": "src/components/PodcastList.jsx",
      "line_number": 14,
      "neg_code": "className={`w-full text-left p-4 rounded-xl transition transform hover:scale-105 ${",
      "pos_code": "className={`w-full text-left p-4 rounded-3xl transition transform hover:scale-105 ${",
      "css_selector": "button.w-full.text-left.p-4",
      "bounding_box": {
        "x": 80,
        "y": 133,
        "width": 736,
        "height": 1075
      }
    },
    {
      "comment": "Bug #9 - grid-template-columns",
      "report_text": "The secondary control sliders are arranged in two columns instead of three, causing misalignment and poor visual balance.",
      "bug_category": "Layout",
      "bug_type": "grid-template-columns",
      "file_modified": "src/components/SecondaryControls.jsx",
      "line_number": 5,
      "neg_code": "<div className=\"grid grid-cols-3 gap-4\">",
      "pos_code": "<div className=\"grid grid-cols-2 gap-4\">",
      "css_selector": "div:has(label:has-text(\"VOLUME\"))",
      "bounding_box": {
        "x": 113,
        "y": 950,
        "width": 670,
        "height": 226
      }
    },
    {
      "comment": "Bug #10 - text-color",
      "report_text": "The stats card labels are rendered in a near-black color and are nearly invisible against the dark background.",
      "bug_category": "Color",
      "bug_type": "text-color",
      "file_modified": "src/components/StatsCard.jsx",
      "line_number": 30,
      "neg_code": "<div className=\"text-sm font-bold text-gray-300 mb-4 flex items-center gap-2\">",
      "pos_code": "<div className=\"text-sm font-bold text-gray-900 mb-4 flex items-center gap-2\">",
      "css_selector": "div:has-text('Today\\'s Stats')",
      "bounding_box": {
        "x": 873,
        "y": 1100,
        "width": 302,
        "height": 20
      }
    }
  ]
}